pynlomic/__init__.py
pynlomic/cfgparse.py
pynlomic/common.py
pynlomic/dataio.py
pynlomic/experimental.py
pynlomic/proc.py
pynlomic/report.py
pynlomic-1.1.0.data/data/scripts/calib_laser_power.py
pynlomic-1.1.0.data/data/scripts/gen_img_report.py
pynlomic-1.1.0.data/data/scripts/lcmicro_to_png_tiff.py
pynlomic-1.1.0.data/data/scripts/make_pipo_tiff_piponator.py
pynlomic-1.1.0.data/data/scripts/make_psf_figure.py
pynlomic-1.1.0.data/data/scripts/parse_custom_pipo_data.py
pynlomic-1.1.0.data/data/scripts/tiff_to_png.py
pynlomic-1.1.0.data/data/test_data/RTT v1_4 PIPO - 11_51_23_.221_.dat.zip
pynlomic-1.1.0.dist-info/LICENSE
pynlomic-1.1.0.dist-info/METADATA
pynlomic-1.1.0.dist-info/WHEEL
pynlomic-1.1.0.dist-info/top_level.txt
pynlomic-1.1.0.dist-info/RECORD
