Metadata-Version: 2.1
Name: pynlomic
Version: 1.1.0
Summary: A Python library for nonlinear microscopy.
Home-page: https://github.com/lukaskontenis/pynlomic
Author: Lukas Kontenis
Author-email: dse.ssd@gmail.com
Classifier: Programming Language :: Python :: 3
Classifier: License :: OSI Approved :: BSD License
Classifier: Operating System :: OS Independent
Requires-Python: >=3.6
License-File: LICENSE
Requires-Dist: numpy >=1.19.5
Requires-Dist: matplotlib >=3.3.3
Requires-Dist: scipy >=1.5.4
Requires-Dist: tifffile >=2020.9.3
Requires-Dist: lkfit >=0.2.0
Requires-Dist: lkcom >=0.4.0
